datahub/__init__.py
datahub/consumer.py
datahub/main.py
datahub/package_version.txt
datahub/source.py
datahub/consumers/__init__.py
datahub/consumers/h5.py
datahub/consumers/merger.py
datahub/consumers/plot.py
datahub/consumers/pshell.py
datahub/consumers/stdout.py
datahub/consumers/table.py
datahub/consumers/txt.py
datahub/sources/__init__.py
datahub/sources/array10.py
datahub/sources/bsread.py
datahub/sources/camserver.py
datahub/sources/daqbuf.py
datahub/sources/databuffer.py
datahub/sources/dispatcher.py
datahub/sources/epics.py
datahub/sources/redis.py
datahub/sources/retrieval.py
datahub/sources/stddaq.py
datahub/utils/__init__.py
datahub/utils/align.py
datahub/utils/bsread.py
datahub/utils/checker.py
datahub/utils/compression.py
datahub/utils/data.py
datahub/utils/net.py
datahub/utils/plot.py
datahub/utils/range.py
datahub/utils/reflection.py
datahub/utils/timing.py
tests/__init__.py
tests/client.py
tests/demo_script.py
tests/demo_sh
tests/test_bsread.py
tests/test_camserver.py
tests/test_chris.py
tests/test_daqbuf.py
tests/test_dash.py
tests/test_dash2.py
tests/test_dash3.py
tests/test_dash4.py
tests/test_dash5.py
tests/test_dash6.py
tests/test_databuffer.py
tests/test_didier.py
tests/test_dispatcher.py
tests/test_epics.py
tests/test_imagebuffer.py
tests/test_imports.py
tests/test_json.py
tests/test_main.py
tests/test_merger.py
tests/test_mult.py
tests/test_plot.py
tests/test_pshell.py
tests/test_range.py
tests/test_redis.py
tests/test_redis_producer.py
tests/test_redis_receiver.py
tests/test_retrieval.py
tests/test_search.py
tests/test_stream.py
tests/test_table.py
tests/test_thread.py
tests/test_timing.py
tests/tst.py
tests/tst2.py
psi_datahub-1.1.5.dist-info/METADATA
psi_datahub-1.1.5.dist-info/WHEEL
psi_datahub-1.1.5.dist-info/entry_points.txt
psi_datahub-1.1.5.dist-info/top_level.txt
psi_datahub-1.1.5.dist-info/RECORD
