Metadata-Version: 2.1
Name: psi-datahub
Version: 1.1.5
Summary: Utilities to retrieve data from PSI sources.
Home-page: https://github.com/paulscherrerinstitute/datahub
Author: Paul Scherrer Institute
Author-email: daq@psi.ch
License: GPLv3
